lavender_icon/__init__.py
lavender_icon/src/icons.json
Lavender_Icon-1.0.3.dist-info/LICENSE
Lavender_Icon-1.0.3.dist-info/METADATA
Lavender_Icon-1.0.3.dist-info/WHEEL
Lavender_Icon-1.0.3.dist-info/top_level.txt
Lavender_Icon-1.0.3.dist-info/RECORD
